mongowriter.py
mongowriter/util.py
mongowriter/__init__.py
mongowriter-0.1.6.dist-info/top_level.txt
mongowriter-0.1.6.dist-info/DESCRIPTION.rst
mongowriter-0.1.6.dist-info/METADATA
mongowriter-0.1.6.dist-info/RECORD
mongowriter-0.1.6.dist-info/metadata.json
mongowriter-0.1.6.dist-info/WHEEL
