Metadata-Version: 2.0
Name: mongowriter
Version: 0.1.6
Summary: Adapter to write documents from a queue to mongodb concurrently
Home-page: https://www.cloudcontrol.com
Author: cloudControl Team
Author-email: info@cloudcontrol.de
License: Apache 2.0
Platform: UNKNOWN
Classifier: Development Status :: 3 - Alpha
Classifier: Intended Audience :: Developers
Classifier: Intended Audience :: Information Technology
Classifier: License :: OSI Approved :: Apache Software License
Classifier: Programming Language :: Python
Classifier: Topic :: Database
Requires-Dist: pymongo (>=2.5,<2.6)
